doom/__init__.py
doom/_version.py
doom/compat.py
doom/fslib.py
doom/lning.py
doom/utils.py
doom/sysinfo/__init__.py
doom/sysinfo/get_local_ip.py
doom/tests/__init__.py
doom/tests/test_compat.py
doom/tests/test_fslib.py
doom/tests/test_get_local_ip.py
doom/tests/test_lning.py
doom/tests/test_utils.py
doom-0.3.2.dist-info/LICENSE.txt
doom-0.3.2.dist-info/METADATA
doom-0.3.2.dist-info/WHEEL
doom-0.3.2.dist-info/entry_points.txt
doom-0.3.2.dist-info/top_level.txt
doom-0.3.2.dist-info/RECORD
