Metadata-Version: 2.1
Name: doom
Version: 0.3.2
Summary: UNKNOWN
Home-page: https://github.com/jbrockmendel/doom
Author: Brock Mendel
Author-email: jbrockmendel@gmail.com
License: MIT
Platform: UNKNOWN
Requires-Dist: six
Requires-Dist: psutil (>=5.0.0)
Requires-Dist: geocoder
